{
    "title": "INtech",
    "link": "http://example.com/interleaved_feed.json",
    "description": "This is a randomly ordered feed of the most recent entries from INtech, skipping any feeds with errors.",
    "lastBuildDate": "2025-11-21T16:10:47.864822",
    "items": [
        {
            "title": "MediaWorld Accidentally Sold iPads for €15 and Asked for Them Back: \"It Was a Clear Mistake\"",
            "link": "https://www.wired.com/story/mediaworld-accidentally-sold-ipads-for-euro15-then-it-asked-for-them-back/",
            "description": "The advantageous offer appeared to loyalty card holders of the European electronics chain on November 8. After 11 days, the company began contacting t...",
            "pubDate": "2025-11-21T19:50:18",
            "image_url": "https://lead-mark.github.io/snippets/genNewsImagesTwo/Picture4.png"
        },
        {
            "title": "X begins rolling out the ‘About this account’ feature to users’ profiles",
            "link": "https://techcrunch.com/2025/11/21/x-begins-rolling-out-the-about-this-account-feature-to-users-profiles/",
            "description": "The feature will show where users are based, how they're connected to X, and how many times they've changed their username.",
            "pubDate": "2025-11-21T18:12:57",
            "image_url": "https://lead-mark.github.io/snippets/genNewsImagesTwo/Picture3.png"
        },
        {
            "title": "These Beats Headphones Are Marked Down to $150 for Black Friday",
            "link": "https://www.wired.com/story/beats-studio-pro-deal-1125/",
            "description": "You can save big on the colorful and bass-forward Beats Studio Pro.",
            "pubDate": "2025-11-21T18:31:00",
            "image_url": "https://lead-mark.github.io/snippets/genNewsImagesTwo/Picture8.png"
        },
        {
            "title": "The 65 Best Deals From REI’s 2025 Holiday Sale",
            "link": "https://www.wired.com/story/rei-holiday-sale-nov-2025/",
            "description": "The company that wants you to #optoutside for Black Friday is having its sale early. Gear up for next year with these great deals on packs, sleeping b...",
            "pubDate": "2025-11-21T19:35:41",
            "image_url": "https://lead-mark.github.io/snippets/genNewsImagesTwo/Picture3.png"
        },
        {
            "title": "Google says hackers stole data from 200 companies following Gainsight breach",
            "link": "https://techcrunch.com/2025/11/21/google-says-hackers-stole-data-from-200-companies-following-gainsight-breach/",
            "description": "Notorious hacking collective Scattered Lapsus$ Hunters takes credit for the breach that affected Salesforce customers’ data, and said it is planning a...",
            "pubDate": "2025-11-21T18:30:27",
            "image_url": "https://lead-mark.github.io/snippets/genNewsImagesTwo/Picture3.png"
        },
        {
            "title": "Impersonators are (still) targeting companies with fake TechCrunch outreach",
            "link": "https://techcrunch.com/2025/11/21/impersonators-are-targeting-companies-with-fake-techcrunch-outreach/",
            "description": "Fraudsters are impersonating TechCrunch reporters and event leads, and reaching out to companies. Here's what we're doing about it, and what you can l...",
            "pubDate": "2025-11-21T17:00:00",
            "image_url": "https://lead-mark.github.io/snippets/genNewsImagesTwo/Picture5.png"
        },
        {
            "title": "The hottest AI wearables and gadgets you can buy right now",
            "link": "https://techcrunch.com/2025/11/21/the-hottest-ai-wearables-and-gadgets-you-can-buy-right-now/",
            "description": "We compiled all the hottest AI wearables currently available, including Bee, Friend, Plaud, and more.",
            "pubDate": "2025-11-21T20:00:00",
            "image_url": "https://lead-mark.github.io/snippets/genNewsImagesTwo/Picture6.png"
        },
        {
            "title": "Best Black Friday Google Pixel Deals (2025)",
            "link": "https://www.wired.com/story/best-black-friday-google-pixel-deals-2025/",
            "description": "Score hundreds off the new Pixel 10 range, or snag a discounted Pixel Watch 4 or Pixel Buds.",
            "pubDate": "2025-11-21T18:08:49",
            "image_url": "https://lead-mark.github.io/snippets/genNewsImagesTwo/Picture8.png"
        },
        {
            "title": "CrowdStrike fires ‘suspicious insider’ who passed information to hackers",
            "link": "https://techcrunch.com/2025/11/21/crowdstrike-fires-suspicious-insider-who-passed-information-to-hackers/",
            "description": "Cybersecurity giant CrowdStrike denied it had been hacked following claims from a hacker group, which leaked screenshots from inside CrowdStrike's net...",
            "pubDate": "2025-11-21T18:55:53",
            "image_url": "https://lead-mark.github.io/snippets/genNewsImagesTwo/Picture8.png"
        },
        {
            "title": "Pranksters Recreated a Working Version of Jeffrey Epstein’s Gmail Inbox",
            "link": "https://www.wired.com/story/pranksters-recreated-a-working-version-of-jeffrey-epstein-gmail-inbox/",
            "description": "Using Jmail, you can read thousands of Jeffrey Epstein’s emails in a familiar format. Use the star function to highlight notable finds.",
            "pubDate": "2025-11-21T19:49:07",
            "image_url": "https://lead-mark.github.io/snippets/genNewsImagesTwo/Picture5.png"
        }
    ]
}