{
    "title": "briefUpdatesMainNLbusinessAndMarkets",
    "link": "http://example.com/interleaved_feed.json",
    "description": "This is a randomly ordered feed of the most recent entries from briefUpdatesMainNLbusinessAndMarkets, skipping any feeds with errors.",
    "lastBuildDate": "2026-01-09T11:00:09.873936",
    "items": [
        {
            "title": "Bill Gates says AI could be used as a bioterrorism weapon akin to the COVID pandemic if it falls into the wrong hands",
            "link": "https://fortune.com/2026/01/09/bill-gates-ai-bad-actors-bioterrorism-threat/",
            "description": "\"We’ll need to be deliberate about how this technology is developed, governed, and deployed,\" Gates wrote.",
            "pubDate": "2026-01-09T14:45:26",
            "image_url": "https://fortune.com/img-assets/wp-content/uploads/2026/01/GettyImages-2237146065-e1767967243270.jpg?w=2048"
        },
        {
            "title": "NASA to make its first-ever medical evacuation from the International Space Station. Here’s why",
            "link": "https://www.fastcompany.com/91471942/nasa-make-first-ever-medical-evacuation-international-space-station-heres-why",
            "description": "In a rare move, NASA is cutting a mission aboard the International Space Station short after an astronaut had a medical issue. The space agency said T...",
            "pubDate": "2026-01-09T15:11:50",
            "image_url": "https://images.fastcompany.com/image/upload/w_1280,q_auto,f_auto,fl_lossy/f_webp,q_auto,c_fit/wp-cms-2/2026/01/AP26008548577300.jpg"
        },
        {
            "title": "3 Fintech Shifts Small Businesses Can’t Afford to Ignore in 2026",
            "link": "https://www.inc.com/james-barrese/3-fintech-shifts-small-businesses-cant-afford-to-ignore-in-2026/91286150",
            "description": "The financial infrastructure is being rebuilt, here’s what you need to know.",
            "pubDate": "2026-01-09T14:00:00",
            "image_url": "https://img-cdn.inc.com/image/upload/f_webp,q_auto,c_fit/vip/2026/01/IMPACT-COUNCIL-AND-INC-LIDERSHIP-FORUM-1-4.png"
        },
        {
            "title": "Philly burbs police stunned by arrest of apparent grave robbery carrying sack with skulls, bones, mummified remains",
            "link": "https://fortune.com/2026/01/09/delaware-county-pennsylvania-suspected-grave-robbery-skulls-bones-mummified-remains/",
            "description": "\"Given the enormity of what we are looking at and the sheer, utter lack of reasonable explanation, it’s difficult to say ... exactly what took place.\"",
            "pubDate": "2026-01-09T14:55:52",
            "image_url": "https://fortune.com/img-assets/wp-content/uploads/2026/01/AP26008735533125.jpg?w=2048"
        },
        {
            "title": "These molecules are remaking manufacturing",
            "link": "https://www.fastcompany.com/91471443/these-molecules-are-remaking-manufacturing",
            "description": "Walk through almost any manufacturing plant today, whether the frontline professionals crushing oilseeds, processing corn, or producing ingredients, a...",
            "pubDate": "2026-01-09T15:00:00",
            "image_url": "https://images.fastcompany.com/image/upload/w_1280,q_auto,f_auto,fl_lossy/f_webp,q_auto,c_fit/wp-cms-2/2026/01/IMPACT-COUNCIL-AND-INC-LIDERSHIP-FORUM-1-6.png"
        },
        {
            "title": "Healthcare subsidies legislation passes in the House, defying GOP leadership",
            "link": "https://www.fastcompany.com/91471952/health-care-subsidies-legislation-passes-house-defying-gop-leadership",
            "description": "In a remarkable rebuke of Republican leadership, the House passed legislation Thursday that would extend expired health care subsidies for those who g...",
            "pubDate": "2026-01-09T14:31:27",
            "image_url": "https://images.fastcompany.com/image/upload/w_1280,q_auto,f_auto,fl_lossy/f_webp,q_auto,c_fit/wp-cms-2/2026/01/AP26005839714528.jpg"
        },
        {
            "title": "Strip out health care and social services, the U.S. lost jobs in 2025—something that usually happens in recessions",
            "link": "https://fortune.com/2026/01/09/jobs-report-december-health-care-federal-reserve/",
            "description": "“It’s fair to call this a hiring recession or a jobless boom,” said economist Heather Long.",
            "pubDate": "2026-01-09T15:19:52",
            "image_url": "https://fortune.com/img-assets/wp-content/uploads/2026/01/GettyImages-2222114730-e1767970753107.jpg?w=2048"
        },
        {
            "title": "GoFundMe confirms that a $1.4 million fundraising campaign for Renee Nicole Good is verified",
            "link": "https://www.fastcompany.com/91471950/renee-nicole-good-gofundme-campaign-is-confirmed-verified",
            "description": "A viral crowd-funding campaign that has raised over $1.4 million and counting for Renee Good has been verified authentic, a spokesperson for GoFundMe ...",
            "pubDate": "2026-01-09T15:20:00",
            "image_url": "https://images.fastcompany.com/image/upload/w_1280,q_auto,f_auto,fl_lossy/f_webp,q_auto,c_fit/wp-cms-2/2026/01/p-2-91471950-gofundme-confirms-campaign-renee-nicole-good.jpg"
        },
        {
            "title": "For Many Startups, CES Is a Prime Hunting Ground For Funding",
            "link": "https://www.inc.com/chris-morris/for-many-startups-ces-is-a-prime-hunting-ground-for-funding/91286213",
            "description": "From the Startup World Cup to Shark Tank auditions, the Consumer Electronics Show has become a destination for raising capital.",
            "pubDate": "2026-01-09T11:30:00",
            "image_url": "https://img-cdn.inc.com/image/upload/f_webp,q_auto,c_fit/vip/2026/01/startups-ces-2026-inc-2254221407.jpg"
        },
        {
            "title": "Sarah Jessica Parker says she only has work-life balance because of the people supporting her: ‘I’m making choices differently than I used to’",
            "link": "https://fortune.com/2026/01/09/sarah-jessica-parker-work-life-balance-carol-burnett-award-golden-globe/",
            "description": "Sarah Jessica Parker took home the 2026 Carrol Burnett award on Thursday.",
            "pubDate": "2026-01-09T15:11:47",
            "image_url": "https://fortune.com/img-assets/wp-content/uploads/2026/01/GettyImages-2224509668-e1767970939626.jpg?w=2048"
        },
        {
            "title": "How I Built a Profitable Company Without Investors",
            "link": "https://www.inc.com/fabienreille/how-i-built-a-profitable-company-without-investors/91286133",
            "description": "Bootstrapping encourages founders to build with intention and grow with discipline.",
            "pubDate": "2026-01-09T14:00:00",
            "image_url": "https://img-cdn.inc.com/image/upload/f_webp,q_auto,c_fit/vip/2026/01/IMPACT-COUNCIL-AND-INC-LIDERSHIP-FORUM-1-3.png"
        },
        {
            "title": "A Booming Economy Doesn’t Help the Job Market",
            "link": "https://www.inc.com/phil-rosen/economic-job-market-outlook-wall-street-fed-rate-cuts-productivity-ai/91286237",
            "description": "More productivity could actually be a negative for labor market growth.",
            "pubDate": "2026-01-09T11:00:00",
            "image_url": "https://img-cdn.inc.com/image/upload/f_webp,q_auto,c_fit/vip/2026/01/job-market-inc-GettyImages-2252257152.jpg"
        },
        {
            "title": "Renee Good’s ex-husband describes her as no kind of activist whatsoever, she was heading home before ICE encounter",
            "link": "https://fortune.com/2026/01/09/was-renee-good-shooting-self-defense-minnesota-activist-protest-ex-husband/",
            "description": "Minneapolis Mayor Jacob Frey says the video recordings show the federal government's self-defense argument is “garbage.”",
            "pubDate": "2026-01-09T15:05:07",
            "image_url": "https://fortune.com/img-assets/wp-content/uploads/2026/01/AP26008727957991-e1767970915659.jpg?w=2048"
        },
        {
            "title": "The World’s Biggest Pappy Van Winkle Bourbon Collection Is About to Go Up for Auction",
            "link": "https://www.inc.com/leila-sheridan/this-million-dollar-whiskey-collection-is-going-up-for-auction/91286196",
            "description": "The collection is filled with vintage American whiskies that are rarely seen.",
            "pubDate": "2026-01-09T15:26:31",
            "image_url": "https://img-cdn.inc.com/image/upload/f_webp,q_auto,c_fit/vip/2026/01/Great-American-Whiskey-Collection.jpg"
        },
        {
            "title": "Meta strikes nuclear power deals in support of its AI data centers",
            "link": "https://www.fastcompany.com/91472050/meta-strikes-nuclear-power-deals-support-ai-data-centers",
            "description": "Facebook parent Meta has reached nuclear power deals with three companies as it continues to look for electricity sources for its artificial intellige...",
            "pubDate": "2026-01-09T14:50:54",
            "image_url": "https://images.fastcompany.com/image/upload/w_1280,q_auto,f_auto,fl_lossy/f_webp,q_auto,c_fit/wp-cms-2/2026/01/AP26008359235826.jpg"
        },
        {
            "title": "It’s fair to say the U.S. was in a hiring recession in 2025: top economist",
            "link": "https://www.marketwatch.com/bulletins/redirect/go?g=d28264cf-001f-4761-9121-cf9c226ff4f1&mod=mw_rss_bulletins",
            "description": "",
            "pubDate": "2026-01-09T14:51:47",
            "image_url": "https://lead-mark.github.io/snippets/genNewsImagesTwo/Picture2.png"
        },
        {
            "title": "‘Modest improvement’ in U.S. economy boosts consumer-sentiment gauge",
            "link": "https://www.marketwatch.com/bulletins/redirect/go?g=8ca46a59-d05f-4629-bfcc-d93d4b4bf4bc&mod=mw_rss_bulletins",
            "description": "",
            "pubDate": "2026-01-09T15:09:10",
            "image_url": "https://lead-mark.github.io/snippets/genNewsImagesTwo/Picture7.png"
        },
        {
            "title": "Bond-market investors quickly shift focus to tariffs from payrolls",
            "link": "https://www.marketwatch.com/bulletins/redirect/go?g=db7b9e2d-7f73-4724-a0b2-863fa5220907&mod=mw_rss_bulletins",
            "description": "",
            "pubDate": "2026-01-09T14:11:59",
            "image_url": "https://lead-mark.github.io/snippets/genNewsImagesTwo/Picture9.png"
        },
        {
            "title": "No Supreme Court decision Friday on legality of Trump’s tariffs",
            "link": "https://www.marketwatch.com/bulletins/redirect/go?g=b5809a92-720b-4212-a8a7-6a4c9bef6615&mod=mw_rss_bulletins",
            "description": "",
            "pubDate": "2026-01-09T15:17:08",
            "image_url": "https://lead-mark.github.io/snippets/genNewsImagesTwo/Picture3.png"
        },
        {
            "title": "The U.S. jobs report appears to suffer from this key defect",
            "link": "https://www.marketwatch.com/bulletins/redirect/go?g=baa2bbeb-a22e-4e21-9332-c50c02e9573d&mod=mw_rss_bulletins",
            "description": "",
            "pubDate": "2026-01-09T14:20:51",
            "image_url": "https://lead-mark.github.io/snippets/genNewsImagesTwo/Picture1.png"
        }
    ]
}