{
    "title": "INsmh",
    "link": "http://example.com/interleaved_feed.json",
    "description": "This is a randomly ordered feed of the most recent entries from INsmh, skipping any feeds with errors.",
    "lastBuildDate": "2025-03-20T13:38:41.388065",
    "items": [
        {
            "title": "Final heartbreaking tribute five children paid for Royal mum who passed away at 46",
            "link": "https://www.mirror.co.uk/news/royals/final-heartbreaking-tribute-five-children-34901608",
            "description": "Archduchess Estelle of Austria sadly died earlier this month at the age of 46. The royal leaves behind her husband Archduke Carl Christian and their f...",
            "pubDate": "2025-03-20T18:27:50",
            "image_url": "https://i2-prod.mirror.co.uk/incoming/article34902005.ece/ALTERNATES/s615/0_PAY-EXCLUSIVE-PICTURES-TAKEN-ON-THE-30112019-The-Archduke-Carl-Christian-wife-Archduchess-Estelle.jpg"
        },
        {
            "title": "Top 10 free activities to boost happiness on International Happiness Day",
            "link": "https://www.mirror.co.uk/money/top-10-free-activities-boost-34901310",
            "description": "While there's no doubt having a bit more money in your pocket makes life's stresses more manageable, many of the things that make us happy don't cost ...",
            "pubDate": "2025-03-20T18:30:07",
            "image_url": "https://i2-prod.mirror.co.uk/incoming/article34902164.ece/ALTERNATES/s615/0_RGP_MDM_310523Dog_25JPG.jpg"
        },
        {
            "title": "The Gangs of London-style crime lord with actress wife who starred in EastEnders",
            "link": "https://www.mirror.co.uk/news/uk-news/gangs-london-style-crime-lord-34899497",
            "description": "Season three of Gangs of London was released on Sky Atlantic today (March 20) and below we look at a notorious mob boss who may have inspired the crea...",
            "pubDate": "2025-03-20T18:00:00",
            "image_url": "https://i2-prod.mirror.co.uk/incoming/article34900849.ece/ALTERNATES/s615/0_gangs444.jpg"
        },
        {
            "title": "Notorious paedophile who ran 'black magic sex cult' to move to 'minimal security' jail",
            "link": "https://www.mirror.co.uk/news/uk-news/notorious-paedophile-who-ran-black-34901509",
            "description": "Serial rapist and paedophile Colin Batley was the self-styled 'high priest' of a 'black magic sex cult' - he now looks set to be moved to an open pris...",
            "pubDate": "2025-03-20T18:21:24",
            "image_url": "https://i2-prod.dailystar.co.uk/incoming/article34901709.ece/ALTERNATES/s615/3_MEDIA-WALES-Colin-Batley-convicted-sex-cult-leader-01.jpg"
        },
        {
            "title": "Birmingham bin strikes: Residents swarm lorry in city plagued by 'rats the size of cats'",
            "link": "https://www.mirror.co.uk/news/uk-news/birmingham-bin-strikes-residents-swarm-34901869",
            "description": "Birmingham locals have been left desperate following a week's worth of strikes, with footage capturing people running at the few rubbish trucks still ...",
            "pubDate": "2025-03-20T18:11:57",
            "image_url": "https://i2-prod.mirror.co.uk/incoming/article34901942.ece/ALTERNATES/s615/0_JS363236555.jpg"
        },
        {
            "title": "Nine English words you probably didn’t know came from Irish",
            "link": "https://metro.co.uk/2025/03/17/nine-english-words-probably-didnt-know-came-irish-22738436/",
            "description": "Some common words we use every day, including the name of one of the UK's main political parties, have a surprising origin in Irish.",
            "pubDate": "2025-03-17T11:54:26",
            "image_url": "https://metro.co.uk/wp-content/uploads/2025/03/SEI_244203926-24ba.jpg?quality=90&strip=all&w=646"
        },
        {
            "title": "Man claims he was shot by his dog while lying in bed",
            "link": "https://metro.co.uk/2025/03/11/man-claims-shot-dog-lying-bed-22709304/",
            "description": "The Memphis man was 'relaxing/talking' in bed when the incident occurred",
            "pubDate": "2025-03-11T17:46:12",
            "image_url": "https://metro.co.uk/wp-content/uploads/2025/03/image-4ed6.png?w=646"
        },
        {
            "title": "‘New Nostradamus’ made eerie prediction about an oil tanker explosion days before it happened",
            "link": "https://metro.co.uk/2025/03/11/new-nostradamus-eerily-predicted-oil-tanker-collision-seven-days-ago-22707001/",
            "description": "'I saw a ship or something in trouble.'",
            "pubDate": "2025-03-11T17:37:42",
            "image_url": "https://metro.co.uk/wp-content/uploads/2025/03/SEC_243447808-7dc1.jpg?quality=90&strip=all&w=646"
        },
        {
            "title": "Who is Mark Carney? New Canadian PM’s family, career, and more",
            "link": "https://metro.co.uk/2025/03/10/mark-carney-new-canadian-pms-family-career-22699934/",
            "description": "Mark Carney met his English wife Diana when they were both members of the Oxford University Ice Hockey Club.",
            "pubDate": "2025-03-10T16:09:59",
            "image_url": "https://metro.co.uk/wp-content/uploads/2025/03/SEI_243255469-846e.jpg?quality=90&strip=all&w=646"
        },
        {
            "title": "Chicken lays anus clenchingly massive egg",
            "link": "https://metro.co.uk/2025/03/07/chicken-lays-anus-clenchingly-massive-egg-22689347/",
            "description": "The whopper took five hours to deliver",
            "pubDate": "2025-03-07T17:06:41",
            "image_url": "https://metro.co.uk/wp-content/uploads/2025/03/SEI_242907831-56fa.jpg?quality=90&strip=all&w=646"
        }
    ]
}