{
    "title": "Individual feed for https://abcnews.go.com/abcnews/topstories",
    "link": "https://abcnews.go.com/abcnews/topstories",
    "description": "Individual feed output.",
    "lastBuildDate": "2025-01-01T13:45:58.264740",
    "items": [
        {
            "title": "LIVE:  15 dead, dozens injured as pickup plows into crowd in New Orleans: ABC News Live",
            "link": "https://abcnews.go.com/Live/video/abcnews-live-41463246",
            "description": "24/7 coverage of breaking news and live events",
            "pubDate": "2025-01-01T18:45:15",
            "image_url": "https://lead-mark.github.io/snippets/genNewsImagesTwo/Picture6.png"
        },
        {
            "title": "15 dead in New Orleans truck attack; suspect ID'd as US citizen, sources say",
            "link": "https://abcnews.go.com/US/1-dead-vehicle-strikes-crowd-new-orleans-police/story?id=117246329",
            "description": "Fifteen people were killed and dozens injured when a pickup truck plowed into a crowd on Bourbon Street in New Orleans.",
            "pubDate": "2025-01-01T18:42:51",
            "image_url": "https://lead-mark.github.io/snippets/genNewsImagesTwo/Picture8.png"
        },
        {
            "title": "Biden says reaction to New Orleans attack was 'anger and frustration'",
            "link": "https://abcnews.go.com/Politics/biden-trump-respond-deadly-new-years-day-attack/story?id=117248268",
            "description": "President Biden said there is \"no justification\" for the \"horrific\" attack early New Year's Day in New Orleans that left at least 10 people dead and d...",
            "pubDate": "2025-01-01T18:07:48",
            "image_url": "https://lead-mark.github.io/snippets/genNewsImagesTwo/Picture2.png"
        },
        {
            "title": "Johnson to meet with Trump at Mar-a-Lago to 'map' strategy ahead of speakership vote",
            "link": "https://abcnews.go.com/Politics/mike-johnson-meet-trump-mar-lago-map-strategy/story?id=117247092",
            "description": "House Speaker Mike Johnson is spending New Year's Day with President-elect Donald Trump ahead of a showdown vote later this week to keep his leadershi...",
            "pubDate": "2025-01-01T14:38:50",
            "image_url": "https://lead-mark.github.io/snippets/genNewsImagesTwo/Picture2.png"
        },
        {
            "title": "Ukraine halts pipeline carrying Russian natural gas to Europe, as deal expires",
            "link": "https://abcnews.go.com/International/ukraine-halts-pipeline-carrying-russian-natural-gas-europe/story?id=117246106",
            "description": "\"We stopped the transit of Russian gas, this is a historic event,\" Herman Galushchenko, Ukraine's energy minister, said in a statement.",
            "pubDate": "2025-01-01T12:56:45",
            "image_url": "https://lead-mark.github.io/snippets/genNewsImagesTwo/Picture4.png"
        }
    ]
}