{
    "title": "Individual feed for https://biggerpockets.com/blog/feed",
    "link": "https://biggerpockets.com/blog/feed",
    "description": "Individual feed output.",
    "lastBuildDate": "2025-01-28T07:31:31.678666",
    "items": [
        {
            "title": "The Middle-Class Trap That Could Keep You from FIRE (How to Escape It)",
            "link": "https://www.biggerpockets.com/blog/money-602",
            "description": "Buying a house, maxing out your 401(k), and leveraging real estate can help you achieve financial independence. But suppose your goal is to retire ear...",
            "pubDate": "2025-01-28T09:00:02",
            "image_url": "https://lead-mark.github.io/snippets/genNewsImagesTwo/Picture4.png"
        },
        {
            "title": "The 5 Best Housing Markets For Short-Term Rentals in 2025",
            "link": "https://www.biggerpockets.com/blog/best-short-term-rental-markets-2025",
            "description": "AirDNA recently released its annual report on the Best Places to Invest in Vacation Rentals, providing valuable insights into the markets investors sh...",
            "pubDate": "2025-01-27T22:47:37",
            "image_url": "https://lead-mark.github.io/snippets/genNewsImagesTwo/Picture3.png"
        },
        {
            "title": "The Beginner’s Guide to Finding (and Funding) Small Multifamily Real Estate",
            "link": "https://www.biggerpockets.com/blog/rookie-515",
            "description": "Small multifamily investing might seem scary to a new investor, but what if we told you these properties are less risky than single-family homes and e...",
            "pubDate": "2025-01-27T09:00:40",
            "image_url": "https://lead-mark.github.io/snippets/genNewsImagesTwo/Picture7.png"
        },
        {
            "title": "10 Hidden Ways to Buy Properties with Huge “Upside”",
            "link": "https://www.biggerpockets.com/blog/real-estate-1075",
            "description": "If you don’t want to make money in real estate, skip this episode. If you hate the idea of having hundreds of thousands or millions of dollars in equi...",
            "pubDate": "2025-01-27T09:00:35",
            "image_url": "https://lead-mark.github.io/snippets/genNewsImagesTwo/Picture8.png"
        },
        {
            "title": "Redfin: Tariff Fears Drive Up Mortgage Rates, Throwing 2025 Off-Track",
            "link": "https://www.biggerpockets.com/blog/on-the-market-290",
            "description": "Could Trump’s proposed tariffs be the reason for the recent rise in mortgage rates? Could this slow the housing market and cause affordability to get ...",
            "pubDate": "2025-01-27T09:00:24",
            "image_url": "https://lead-mark.github.io/snippets/genNewsImagesTwo/Picture4.png"
        }
    ]
}