{
    "title": "Individual feed for https://fitr365.com/feed",
    "link": "https://fitr365.com/feed",
    "description": "Individual feed output.",
    "lastBuildDate": "2025-04-27T02:11:58.805343",
    "items": [
        {
            "title": "error",
            "link": "error",
            "description": "error",
            "pubDate": "2025-04-27T02:11:58.804928",
            "image_url": "error"
        },
        {
            "title": "error",
            "link": "error",
            "description": "error",
            "pubDate": "2025-04-27T02:11:58.804933",
            "image_url": "error"
        },
        {
            "title": "error",
            "link": "error",
            "description": "error",
            "pubDate": "2025-04-27T02:11:58.804936",
            "image_url": "error"
        }
    ]
}