{
    "title": "Individual feed for https://lead-mark.github.io/snippets/InboxNews/INhealth.xml",
    "link": "https://lead-mark.github.io/snippets/InboxNews/INhealth.xml",
    "description": "Individual feed output.",
    "lastBuildDate": "2025-01-03T13:43:30.347673",
    "items": [
        {
            "title": "12 Things That Happen When You Quit Drinking",
            "link": "https://www.webmd.com/mental-health/addiction/ss/slideshow-quit-alcohol-effects",
            "description": "",
            "pubDate": "2025-01-03T06:34:08",
            "image_url": "https://lead-mark.github.io/snippets/genNewsImagesTwo/Picture1.png"
        },
        {
            "title": "Achieve Big Changes With Small Steps",
            "link": "https://www.webmd.com/balance/big-changes-small-steps",
            "description": "New Year’s resolutions can be achievable without feeling daunting. Discover how small, steady steps can help you reach your health and wellness goals ...",
            "pubDate": "2025-01-03T06:34:08",
            "image_url": "https://lead-mark.github.io/snippets/genNewsImagesTwo/Picture5.png"
        },
        {
            "title": "What It’s Like to Have Seasonal Affective Disorder",
            "link": "https://www.webmd.com/depression/features/seasonal-affective-disorder",
            "description": "",
            "pubDate": "2025-01-03T06:34:08",
            "image_url": "https://lead-mark.github.io/snippets/genNewsImagesTwo/Picture7.png"
        },
        {
            "title": "This Zodiac Sign Could Have The Worst Luck With Money In 2025",
            "link": "https://www.mindbodygreen.com/articles/this-zodiac-sign-could-have-unlucky-financial-year-in-2025",
            "description": "You've been warned!",
            "pubDate": "2025-01-03T01:01:00",
            "image_url": "https://lead-mark.github.io/snippets/genNewsImagesTwo/Picture2.png"
        },
        {
            "title": "This Zodiac Sign Can Expect The Luckiest Year In Love In 2025",
            "link": "https://www.mindbodygreen.com/articles/which-zodiac-sign-can-expect-luckiest-year-in-love-in-2025",
            "description": "Ooh la la.",
            "pubDate": "2025-01-03T00:31:00",
            "image_url": "https://lead-mark.github.io/snippets/genNewsImagesTwo/Picture9.png"
        }
    ]
}