{
    "title": "Individual feed for https://muscleandfitness.com/rss.xml",
    "link": "https://muscleandfitness.com/rss.xml",
    "description": "Individual feed output.",
    "lastBuildDate": "2025-01-15T16:16:44.093365",
    "items": [
        {
            "title": "error",
            "link": "error",
            "description": "error",
            "pubDate": "2025-01-15T16:16:44.092860",
            "image_url": "error"
        },
        {
            "title": "error",
            "link": "error",
            "description": "error",
            "pubDate": "2025-01-15T16:16:44.092890",
            "image_url": "error"
        },
        {
            "title": "error",
            "link": "error",
            "description": "error",
            "pubDate": "2025-01-15T16:16:44.092906",
            "image_url": "error"
        }
    ]
}