{
    "title": "Individual feed for https://rwjbh.org/blog/feed",
    "link": "https://rwjbh.org/blog/feed",
    "description": "Individual feed output.",
    "lastBuildDate": "2025-03-18T06:32:07.278883",
    "items": [
        {
            "title": "error",
            "link": "error",
            "description": "error",
            "pubDate": "2025-03-18T06:32:07.278601",
            "image_url": "error"
        },
        {
            "title": "error",
            "link": "error",
            "description": "error",
            "pubDate": "2025-03-18T06:32:07.278606",
            "image_url": "error"
        },
        {
            "title": "error",
            "link": "error",
            "description": "error",
            "pubDate": "2025-03-18T06:32:07.278610",
            "image_url": "error"
        }
    ]
}