{
    "title": "Individual feed for https://seekingalpha.com/feed.xml",
    "link": "https://seekingalpha.com/feed.xml",
    "description": "Individual feed output.",
    "lastBuildDate": "2025-11-01T01:08:40.415036",
    "items": [
        {
            "title": "Energy Fuels: Earnings Preview And Growth Outlook",
            "link": "https://seekingalpha.com/article/4836625-energy-fuels-earnings-preview-and-growth-outlook?source=feed_all_articles",
            "description": "",
            "pubDate": "2025-11-01T06:03:21",
            "image_url": "https://lead-mark.github.io/snippets/genNewsImagesTwo/Picture6.png"
        },
        {
            "title": "Markets Weekly Outlook - BoE Meeting In Focus, U.S. Government Shutdown Continues",
            "link": "https://seekingalpha.com/article/4836628-markets-weekly-outlook-boe-meeting-in-focus-us-government-shutdown-continues?source=feed_all_articles",
            "description": "",
            "pubDate": "2025-11-01T05:55:00",
            "image_url": "https://lead-mark.github.io/snippets/genNewsImagesTwo/Picture9.png"
        },
        {
            "title": "Lincoln National's Turnaround Impresses (Rating Upgrade)",
            "link": "https://seekingalpha.com/article/4836624-lincoln-nationals-turnaround-impresses-upgrade?source=feed_all_articles",
            "description": "",
            "pubDate": "2025-11-01T05:53:39",
            "image_url": "https://lead-mark.github.io/snippets/genNewsImagesTwo/Picture6.png"
        },
        {
            "title": "S&P 500 Snapshot: Index Posts 2.3% Gain In October",
            "link": "https://seekingalpha.com/article/4836620-sp-500-snapshot-index-posts-2-3-percent-gain-october?source=feed_all_articles",
            "description": "",
            "pubDate": "2025-11-01T05:30:00",
            "image_url": "https://lead-mark.github.io/snippets/genNewsImagesTwo/Picture5.png"
        },
        {
            "title": "Banks Borrow Record $50 Billion At Fed's New SRF Amid Hot Repo Rates, ON RRPs Spike To $52 Billion In Opposite Direction",
            "link": "https://seekingalpha.com/article/4836626-banks-borrow-record-50b-at-fed-new-srf-amid-hot-repo-rates-on-rrp-spike-to-52b?source=feed_all_articles",
            "description": "",
            "pubDate": "2025-11-01T05:30:00",
            "image_url": "https://lead-mark.github.io/snippets/genNewsImagesTwo/Picture9.png"
        }
    ]
}