{
    "title": "Individual feed for https://www.nytimes.com/svc/collections/v1/publish/https://www.nytimes.com/section/world/rss.xml",
    "link": "https://www.nytimes.com/svc/collections/v1/publish/https://www.nytimes.com/section/world/rss.xml",
    "description": "Individual feed output.",
    "lastBuildDate": "2025-07-29T06:42:35.655522",
    "items": [
        {
            "title": "Russian Strike on Prison Kills 16, Ukraine Says",
            "link": "https://www.nytimes.com/2025/07/29/world/europe/ukraine-russia-trump.html",
            "description": "The attack, which came just hours after President Trump gave the Kremlin a new deadline to work toward ending the war, was part of a wave across the c...",
            "pubDate": "2025-07-29T11:23:00",
            "image_url": "https://lead-mark.github.io/snippets/genNewsImagesTwo/Picture7.png"
        },
        {
            "title": "Europe Made Major Trade Concessions to Trump. How Did That Happen?",
            "link": "https://www.nytimes.com/2025/07/29/world/europe/europe-trump-trade-concessions-analysis.html",
            "description": "Some European politicians are dismayed that the European Union did not drive a harder bargain, but facing the threat of a damaging trade war, official...",
            "pubDate": "2025-07-29T10:53:57",
            "image_url": "https://lead-mark.github.io/snippets/genNewsImagesTwo/Picture2.png"
        },
        {
            "title": "Deadly Flooding Inundates Beijing",
            "link": "https://www.nytimes.com/video/world/asia/100000010310810/beijing-china-floods.html",
            "description": "Severe rains caused flooding and landslides in Beijing and surrounding areas, leaving homes destroyed as mass evacuations were underway.",
            "pubDate": "2025-07-29T10:43:57",
            "image_url": "https://lead-mark.github.io/snippets/genNewsImagesTwo/Picture3.png"
        },
        {
            "title": "North Korea Says Kim’s Relations With Trump ‘Not Bad,’ but Stands Firm on Nukes",
            "link": "https://www.nytimes.com/2025/07/29/world/asia/north-korea-kim-trump.html",
            "description": "The country appeared to signal an openness to talks, but said it must be recognized as a nuclear power and would not discuss abandoning its arsenal.",
            "pubDate": "2025-07-29T10:30:54",
            "image_url": "https://lead-mark.github.io/snippets/genNewsImagesTwo/Picture9.png"
        },
        {
            "title": "Heavy Rain and Flooding in China Kill at Least 30",
            "link": "https://www.nytimes.com/2025/07/28/world/asia/china-rain-beijing-deaths.html",
            "description": "The rains set off flooding and landslides, forcing tens of thousands of people to flee their homes in the capital and neighboring Hebei Province.",
            "pubDate": "2025-07-29T10:26:48",
            "image_url": "https://lead-mark.github.io/snippets/genNewsImagesTwo/Picture1.png"
        }
    ]
}