{
    "title": "Individual feed for https://www.newsmax.com/rss/Politics/1/",
    "link": "https://www.newsmax.com/rss/Politics/1/",
    "description": "Individual feed output.",
    "lastBuildDate": "2025-10-01T06:55:30.609585",
    "items": [
        {
            "title": "N.Y. AG James Sues DHS for Nearly $34M Over Transit Funding Freeze",
            "link": "https://www.newsmax.com/politics/ag-transit-dhs/2025/10/01/id/1228546",
            "description": "New York Attorney General Letitia James on Tuesday filed a lawsuit and an emergency motion seeking a temporary restraining order against U.S. Secretar...",
            "pubDate": "2025-10-01T11:21:54",
            "image_url": "https://www.newsmax.com/cmspages/getfile.aspx?guid=0C660B61-BA0E-4698-9E26-C8663EF9C526"
        },
        {
            "title": "What Happens Now With Govt Shutdown Underway",
            "link": "https://www.newsmax.com/politics/government-shutdown-chuck-schumer/2025/10/01/id/1228545",
            "description": "Washington is bracing for what could be a prolonged federal shutdown after lawmakers deadlocked and missed the deadline for funding the government.",
            "pubDate": "2025-10-01T11:15:17",
            "image_url": "https://www.newsmax.com/cmspages/getfile.aspx?guid=7DBBF408-6A58-47DB-A28A-1765D94D4C5D"
        },
        {
            "title": "Jack, Jimmy McCain Floated for Schweikert's House Seat",
            "link": "https://www.newsmax.com/politics/mccain-schweikert-arizona/2025/10/01/id/1228541",
            "description": "Within moments of Rep. David Schweikert making official Tuesday his decision to seek the Republican nomination for governor of Arizona in 2026, and va...",
            "pubDate": "2025-10-01T10:51:40",
            "image_url": "https://www.newsmax.com/cmspages/getfile.aspx?guid=B26F2C81-AFBD-425B-8D30-093B77C0A81C"
        },
        {
            "title": "Govt Shutdown Begins After Senate Dems Reject CR",
            "link": "https://www.newsmax.com/politics/democrats-senate-government/2025/10/01/id/1228534",
            "description": "Plunged into a government shutdown, the U.S. is confronting a fresh cycle of uncertainty after Democrats failed to vote for a continuing resolution to...",
            "pubDate": "2025-10-01T05:08:13",
            "image_url": "https://www.newsmax.com/cmspages/getfile.aspx?guid=44D0F1E4-B9CD-4726-9611-E7E319EC8240"
        },
        {
            "title": "Pope Leo Backs Sen. Durbin Award Despite Pro-Abortion Stand",
            "link": "https://www.newsmax.com/politics/pope-leo-xiv-catholic-church-dick-durbin/2025/09/30/id/1228533",
            "description": "Pope Leo XIV has stepped into a growing controversy in the American Catholic Church, signaling support for honoring Sen. Dick Durbin, D-Ill., with a C...",
            "pubDate": "2025-10-01T04:08:22",
            "image_url": "https://www.newsmax.com/cmspages/getfile.aspx?guid=41FE87AA-4BE7-4AA0-A818-126B1CC41B02"
        }
    ]
}