{
    "title": "MYB",
    "link": "http://example.com/interleaved_feed.json",
    "description": "This is a randomly ordered feed of the most recent entries from MYB, skipping any feeds with errors.",
    "lastBuildDate": "2026-01-29T17:25:07.520141",
    "items": [
        {
            "title": "A Psychologist Shares A Test That Uncovers Your ‘Hidden Superpower’ — Rooted In Personality Research",
            "link": "https://www.forbes.com/sites/traversmark/2026/01/29/a-psychologist-shares-a-test-that-uncovers-your-hidden-superpower---rooted-in-personality-research/",
            "description": "Most of us try to be good at everything. This test reveals the one thing you should actually be doubling down on.",
            "pubDate": "2026-01-29T20:46:42",
            "image_url": "https://imageio.forbes.com/specials-images/imageserve/697bc5b95c1e81222e81d6aa/0x0.jpg?width=960"
        },
        {
            "title": "‘God Of War’ Just Cast A ‘Princess Bride’ Actor As Its Next Norse God",
            "link": "https://www.forbes.com/sites/erikkain/2026/01/29/god-of-war-casting-news-mandy-patinkin-odin/",
            "description": "God of War just cast its next Norse god for the upcoming live-action video game adaptation.",
            "pubDate": "2026-01-29T21:52:04",
            "image_url": "https://imageio.forbes.com/specials-images/imageserve/697bd22ed8a70813b43c0d89/0x0.jpg?width=960"
        },
        {
            "title": "‘The White Lotus’ Season 4 Officially Casts Its Next Three Actors",
            "link": "https://www.forbes.com/sites/erikkain/2026/01/29/the-white-lotus-season-4-casting-helena-bonham-carter/",
            "description": "Helena Bonham Carter joins the cast of 'The White Lotus' Season 4, along with two new casting announcements.",
            "pubDate": "2026-01-29T21:25:26",
            "image_url": "https://imageio.forbes.com/specials-images/imageserve/697bc722ced959e7f9b8829d/0x0.jpg?width=960"
        },
        {
            "title": "Animated AI Film Festival Shorts To Be Shown In U.S. Theaters In February",
            "link": "https://www.forbes.com/sites/bennyhareven/2026/01/29/animated-ai-film-festival-shorts-to-be-shown-in-us-theaters-in-february/",
            "description": "The first Frame Forward Animated AI Film Festival will be pushing three AI-tool created short films in U.S theaters this month – but the soul of anima...",
            "pubDate": "2026-01-29T22:16:10",
            "image_url": "https://imageio.forbes.com/specials-images/imageserve/697bdb85a46470f645ce71cc/0x0.jpg?width=960"
        },
        {
            "title": "Why World Models Like Google’s Project Genie Work",
            "link": "https://www.forbes.com/sites/amirhusain/2026/01/29/why-world-models-like-googles-project-genie-work/",
            "description": "Google's Genie generates infinite interactive worlds from text. The secret? AI models compress reality's rules into transferable principles, enabling ...",
            "pubDate": "2026-01-29T21:38:44",
            "image_url": "https://imageio.forbes.com/specials-images/imageserve/697bd152501203a89c163882/0x0.jpg?width=960"
        },
        {
            "title": "Skepticism, surprise and resistance",
            "link": "https://seths.blog/2026/01/skepticism-surprise-and-resistance/",
            "description": "Every important medical innovation of the last five hundred years has been ridiculed, undermined and ignored by doctors and the medical establishment....",
            "pubDate": "2026-01-29T10:03:00",
            "image_url": "https://lead-mark.github.io/snippets/genNewsImagesTwo/Picture5.png"
        },
        {
            "title": "On the hiring line",
            "link": "https://seths.blog/2026/01/on-the-hiring-line/",
            "description": "There have always been two sides: Hiring people to do tasks and jobs, or hoping to be hired to do those tasks and jobs. The difference now is that it’...",
            "pubDate": "2026-01-28T10:03:00",
            "image_url": "https://lead-mark.github.io/snippets/genNewsImagesTwo/Picture10.png"
        },
        {
            "title": "Insulation > power",
            "link": "https://seths.blog/2026/01/insulation-power/",
            "description": "When energy is cheap, people build buildings that are poorly insulated. It’s faster and cheaper in the short run. In the long run, though, insulation ...",
            "pubDate": "2026-01-27T10:03:00",
            "image_url": "https://lead-mark.github.io/snippets/genNewsImagesTwo/Picture8.png"
        },
        {
            "title": "Terrible",
            "link": "https://seths.blog/2026/01/terrible/",
            "description": "Most of us are terrible at some things. Lack of skill, focus, practice, care or just temperament means that we don’t do the task as well as we might. ...",
            "pubDate": "2026-01-26T10:03:00",
            "image_url": "https://lead-mark.github.io/snippets/genNewsImagesTwo/Picture10.png"
        },
        {
            "title": "In defense of popups",
            "link": "https://seths.blog/2026/01/in-defense-of-popups/",
            "description": "One friend recently opened a bookstore instead of a bookmobile. Another is investing two years of his life to open a restaurant instead of a series of...",
            "pubDate": "2026-01-25T10:03:00",
            "image_url": "https://lead-mark.github.io/snippets/genNewsImagesTwo/Picture10.png"
        }
    ]
}