{
    "title": "SevenAtSevenLastSection",
    "link": "http://example.com/interleaved_feed.json",
    "description": "This is a randomly ordered feed of the most recent entries from SevenAtSevenLastSection, skipping any feeds with errors.",
    "lastBuildDate": "2025-06-26T11:04:24.181356",
    "items": [
        {
            "title": "Judges in Missouri Can Levy Death if Juries Deadlock. Some Say the Law Is Unconstitutional.",
            "link": "https://www.themarshallproject.org/2025/06/26/missouri-death-penalty-judges",
            "description": "Missouri is one of two states where a judge can hand down death when juries cannot agree unanimously on a sentence.",
            "pubDate": "2025-06-26T11:00:00",
            "image_url": "https://mirrorball.themarshallproject.org/jgXXHWvFdd1DUQ67mHURuWA5hRvfOp-2K8HzWCrAfok/w:1200/aHR0cHM6Ly9kMm0x/OXBtdnRzNWJvYi5j/bG91ZGZyb250Lm5l/dC96eTFxemR4cnhx/MTByMmtwdjh6anl2/cHY1b3pwLzI1MDYy/MF9LaW1fU1RMLUpV/REdFLURFQVRILVBF/TkFMVFlfaGVhZGVy/LmpwZw"
        },
        {
            "title": "6 Health Symptoms You Shouldn’t Ignore",
            "link": "https://www.webmd.com/heart-disease/serious-symptoms-not-ignore",
            "description": "Some symptoms may seem minor, but they could signal something more serious. Learn 6 signs you should never ignore -- and what they might mean.",
            "pubDate": "2025-06-26T11:53:14",
            "image_url": "https://img.lb.wbmdstatic.com/vim/live/webmd/consumer_assets/site_images/article_thumbnails/other/woman-holding-back-of-sore-calf-muscle-other/1800x1200-woman-holding-back-of-sore-calf-muscle-other.jpg?resize=484px:*&output-quality=70"
        },
        {
            "title": "Your Annual Checkup Could Catch More Than You Think",
            "link": "https://www.webmd.com/a-to-z-guides/annual-physical-examinations",
            "description": "",
            "pubDate": "2025-06-26T11:53:14",
            "image_url": "https://img.lb.wbmdstatic.com/vim/live/webmd/consumer_assets/site_images/article_thumbnails/other/stethoscope-on-mans-chest-close-up-other/1800x1200-stethoscope-on-mans-chest-close-up-other.jpg?resize=484px:*&output-quality=70"
        },
        {
            "title": "Summer Releases by Latine Authors",
            "link": "https://bookriot.com/summer-2025-releases-by-latine-authors/",
            "description": "This summer is stacked with new releases by Latine authors, from witchy academia to a borderlands retelling of Persephone and Demeter.",
            "pubDate": "2025-06-26T11:05:00",
            "image_url": "https://s2982.pcdn.co/wp-content/uploads/2025/06/summer-2025-releases-latine-authors.jpg.optimal.jpg"
        },
        {
            "title": "This Sapphic, College-Set Graphic Novel Is Perfect for Fans of HEARTSTOPPER",
            "link": "https://bookriot.com/this-sapphic-college-set-graphic-novel-is-perfect-for-fans-of-heartstopper/",
            "description": "This graphic novel has bubble gum cuteness, and delivers on the cozy, the cathartic, and the cute.",
            "pubDate": "2025-06-26T13:30:00",
            "image_url": "https://s2982.pcdn.co/wp-content/uploads/2025/06/partial-cover-of-If-Youll-Have-Me-by-Eunnie-2.jpg.optimal.jpg"
        },
        {
            "title": "What Dehydration-Related Migraines Really Feel Like",
            "link": "https://www.webmd.com/migraines-headaches/migraine-dehydration-link",
            "description": "",
            "pubDate": "2025-06-26T11:53:14",
            "image_url": "https://img.lb.wbmdstatic.com/vim/live/webmd/consumer_assets/site_images/articles/health_tools/how_caffeine_affects_your_body_slideshow/1800ss_getty_rf_woman_experiencing_hot_flash.jpg?resize=484px:*&output-quality=70"
        },
        {
            "title": "Get Ready for The Most Anticipated Romance Sequels Out in 2025",
            "link": "https://bookriot.com/romance-sequels-out-in-2025/",
            "description": "Waiting for the sequels of books we love is not for the weak of heart. Check out the most anticipated romance sequels out in 2025.",
            "pubDate": "2025-06-26T11:06:00",
            "image_url": "https://s2982.pcdn.co/wp-content/uploads/2025/06/off-center-collage-2.jpg.optimal.jpg"
        },
        {
            "title": "Fringe Forward",
            "link": "https://juliaberolzheimer.com/2025/06/fringe-forward/",
            "description": "Mango Top, Michael Kors Skirt, Hunting Season Bag, Gianvito Rossi Sandals There’s something undeniably captivating about fringe in the summertime, the...",
            "pubDate": "2025-06-26T05:00:49",
            "image_url": "https://juliaberolzheimer.com/wp-content/uploads/2025/06/20250515-jb-mango-top-michael-kors-skirt-1003327-1024x1536.jpg"
        },
        {
            "title": "The Bestselling Books of the Week, According to All the Lists",
            "link": "https://bookriot.com/the-bestselling-books-of-the-week-june-26-2025/",
            "description": "USA Today, Publishers Weekly, NYT, Amazon, and Indie Booksellers all have their own bestseller lists. Here are the combined results.",
            "pubDate": "2025-06-26T11:10:00",
            "image_url": "https://s2982.pcdn.co/wp-content/uploads/2025/06/bookstore.jpg.optimal.jpg"
        },
        {
            "title": "June’s New YA Nonfiction and YA Comic Releases",
            "link": "https://bookriot.com/junes-new-ya-nonfiction-and-ya-comic-releases/",
            "description": "From pro-surfing to road trips gone bad, check out June's new YA nonfiction and YA comics releases.",
            "pubDate": "2025-06-26T14:00:00",
            "image_url": "https://s2982.pcdn.co/wp-content/uploads/2025/06/new-ya-nonfiction-comics-june-2025.jpg.optimal.jpg"
        },
        {
            "title": "Amazon Edit: The High-Summer Capsule",
            "link": "https://juliaberolzheimer.com/2025/06/amazon-edit-the-high-summer-capsule-2/",
            "description": "Lioness Top & Skirt, Similar Sandals Our latest Amazon edit is a curated selection of pieces that feel elevated yet… The post Amazon Edit: The High-Su...",
            "pubDate": "2025-06-25T05:00:53",
            "image_url": "https://juliaberolzheimer.com/wp-content/uploads/2025/06/20250618-jb-lioness-tank-skirt-1020161-1024x1538.jpg"
        },
        {
            "title": "Children’s science television: Not just for children",
            "link": "https://childandfamilyblog.com/childrens-science-television-not-just-for-children/?utm_source=rss&utm_medium=rss&utm_campaign=childrens-science-television-not-just-for-children",
            "description": "Key takeaways for caregivers Parents sometimes avoid talking about science with their children, fearing they might provide inaccurate or misleading in...",
            "pubDate": "2025-06-24T17:13:32",
            "image_url": "https://childandfamilyblog.com/wp-content/uploads/2025/05/pexels-silverkblack-22690891-scaled.jpg"
        },
        {
            "title": "Sheer Genius",
            "link": "https://juliaberolzheimer.com/2025/06/sheer-genius/",
            "description": "Chan Luu Dress, Cuup Bra, The Row Skirt (old, similar here), Margaux Sandals, Miu Miu Bag (old, similar here and here), Arielle Ratner Necklace, Tiny ...",
            "pubDate": "2025-06-24T05:00:40",
            "image_url": "https://juliaberolzheimer.com/wp-content/uploads/2025/06/20250614-jb-chan-luu-dress-cuup-bra-the-row-skirt-1009866-1024x1536.jpg"
        },
        {
            "title": "How Ohio Prison Staff Open and Read Confidential Legal Mail",
            "link": "https://www.themarshallproject.org/2025/06/23/legal-ohio-prison-mail-attorney-client-constitutional",
            "description": "An anti-drug smuggling policy has slowed the delivery of time-sensitive court documents as prison staff read letters protected by attorney-client priv...",
            "pubDate": "2025-06-23T11:00:22",
            "image_url": "https://mirrorball.themarshallproject.org/3FIePT26gUihSi5M3kTzL7KgEux9rBdsQOlEbpHnRgw/w:1200/aHR0cHM6Ly9kMm0x/OXBtdnRzNWJvYi5j/bG91ZGZyb250Lm5l/dC9obnJmazczNTFq/b21za3ZubXJjNmI3/MTY2eWprLzI1MDYx/OC1DTEUtTEVHQUwt/TUFJTC1JYnJhaGlt/LVJheWludGFrYXRo/LmpwZw"
        },
        {
            "title": "Summer In A Softer Light",
            "link": "https://juliaberolzheimer.com/2025/06/summer-in-a-softer-light/",
            "description": "Outfit Details: Johanna Ortiz Dress (love this one and this one on sale), Gianvitto Rossi Sandals (heeled version here), Similar… The post Summer In A...",
            "pubDate": "2025-06-23T05:00:16",
            "image_url": "https://juliaberolzheimer.com/wp-content/uploads/2025/06/20250520-jb-johanna-ortiz-dress-1005856-1024x1536.jpg"
        },
        {
            "title": "Teriyaki Meatball Foil Packets",
            "link": "https://therecipecritic.com/meatball-foil-packets/",
            "description": "My meatball foil packets have juicy meatballs, sweet pineapple, colorful veggies, covered in sticky teriyaki sauce, and grilled to perfection.…",
            "pubDate": "2025-06-22T13:00:00",
            "image_url": "https://therecipecritic.com/wp-content/uploads/2025/06/teriyaki-meatballs.jpg"
        },
        {
            "title": "These States Are Debating Castration for Sex Crimes. Experts Call It Cruel and Pointless.",
            "link": "https://www.themarshallproject.org/2025/06/21/sex-offender-law-louisiana-castration-crime",
            "description": "Critics say there’s no evidence that castration prevents future sex offenses. Yet several states are weighing such measures.",
            "pubDate": "2025-06-21T17:00:00",
            "image_url": "https://mirrorball.themarshallproject.org/4VxebPq-Q-2c0zSnmdqQN0HKk0kRdLuL1JQ2GWrDnCs/w:1200/aHR0cHM6Ly9kMm0x/OXBtdnRzNWJvYi5j/bG91ZGZyb250Lm5l/dC9nZXh3aGlsdGwz/aXYyMXljOWEzMGdj/bzlrcjA3LzI1MDYy/MF9HZXR0eV9DQUVT/U0FZMDYyMV9zb2Np/YWwuanBn"
        },
        {
            "title": "He Spent Years in Federal Prisons. Now He’s Helping to Lead Them.",
            "link": "https://www.themarshallproject.org/2025/06/20/josh-smith-bureau-of-prisons-reaction",
            "description": "The Bureau of Prisons’ new deputy director’s past incarceration has drawn outrage from some officers — and support from people still inside.",
            "pubDate": "2025-06-20T11:00:37",
            "image_url": "https://mirrorball.themarshallproject.org/VrmsIeH_hHnixqaBXOk0ObW-jan1L8sznUaWJtTTSaE/w:1200/aHR0cHM6Ly9kMm0x/OXBtdnRzNWJvYi5j/bG91ZGZyb250Lm5l/dC9xdmN6N2FrdnBl/Ym9id3hpY2RsYnJy/N2h3Z2ZuL1VTQVRT/SV8xOTA3ODQ3NS5q/cGc"
        },
        {
            "title": "Grab and Go Meal Plan",
            "link": "https://therecipecritic.com/grab-and-go-meal-plan/",
            "description": "Between school pickups, errands, and everything else, dinner shouldn’t be the hard part. This grab-and-go meal plan has five easy…",
            "pubDate": "2025-06-20T13:00:00",
            "image_url": "https://therecipecritic.com/wp-content/uploads/2025/06/Grab-and-Go-Meal-Plan-1-1.png"
        },
        {
            "title": "Cart Confidential Vol. 19",
            "link": "https://juliaberolzheimer.com/2025/06/cart-confidential-vol-19/",
            "description": "The end of June finds us in a sun-drenched rhythm, where days spill into one another with salt-kissed ease. We’re… The post Cart Confidential Vol. 19 ...",
            "pubDate": "2025-06-20T05:00:51",
            "image_url": "https://lead-mark.github.io/snippets/genNewsImagesTwo/Picture10.png"
        },
        {
            "title": "A North Carolina County Wanted New Court to Stem Its Opioid Crisis. Then Came Trump’s Cuts.",
            "link": "https://www.themarshallproject.org/2025/06/17/north-carolina-recovery-court-trump-funding-cuts",
            "description": "As the Justice Department slashes funding to programs across the U.S., Wilkes County’s planned recovery court was halted before it started.",
            "pubDate": "2025-06-17T11:00:00",
            "image_url": "https://mirrorball.themarshallproject.org/iRiYGBTjBK6PNQHAPKgM9FD1cGjnv51Skrc5rjMuIUw/w:1200/aHR0cHM6Ly9kMm0x/OXBtdnRzNWJvYi5j/bG91ZGZyb250Lm5l/dC9hMmtwZG1icnBx/cDd3OWtidXRoejZ4/M3ZobjdtLzI1MDYx/My1MQVpBUlVTLUdS/QU5ULUpDb29rLW1p/c3R5LmpwZw"
        },
        {
            "title": "Prenatal stress and children’s behavior: What expectant parents should know",
            "link": "https://childandfamilyblog.com/prenatal-stress-and-childrens-behavior/?utm_source=rss&utm_medium=rss&utm_campaign=prenatal-stress-and-childrens-behavior",
            "description": "Key takeaways for caregivers Mental health support during pregnancy benefits both parents and children. Research shows that pregnant adults’ psycholog...",
            "pubDate": "2025-06-17T02:34:35",
            "image_url": "https://childandfamilyblog.com/wp-content/uploads/2025/03/pexels-rdne-6149341-scaled.jpg"
        },
        {
            "title": "Creamy Boat Dip",
            "link": "https://therecipecritic.com/boat-dip/",
            "description": "This viral boat dip is blowing up on the socials, and for good reason. It’s creamy, cheesy, and the best…",
            "pubDate": "2025-06-16T13:00:00",
            "image_url": "https://therecipecritic.com/wp-content/uploads/2025/06/boat-dip.jpg"
        },
        {
            "title": "Weekly Meal Plan #48",
            "link": "https://therecipecritic.com/weekly-meal-plan-48/",
            "description": "Need a break from the whole “what’s for dinner?” struggle? I’ve got you covered with this week’s meal plan. With…",
            "pubDate": "2025-06-13T13:00:00",
            "image_url": "https://therecipecritic.com/wp-content/uploads/2025/06/Week-48-Meal-Plan-Collage-.jpg"
        },
        {
            "title": "The Perfect Arnold Palmer",
            "link": "https://therecipecritic.com/arnold-palmer-recipe/",
            "description": "If you love iced tea, you’re going to be obsessed with this Arnold Palmer. The combo of crisp black tea…",
            "pubDate": "2025-06-10T13:00:00",
            "image_url": "https://therecipecritic.com/wp-content/uploads/2025/05/arnold-palmer-.jpg"
        },
        {
            "title": "Controversies around children and digital technology",
            "link": "https://childandfamilyblog.com/children-and-digital-technology/?utm_source=rss&utm_medium=rss&utm_campaign=children-and-digital-technology",
            "description": "Key takeaways for caregivers Many caregivers and policymakers around the world are concerned about possible effects of excessive screen time on childr...",
            "pubDate": "2025-06-09T23:13:08",
            "image_url": "https://childandfamilyblog.com/wp-content/uploads/2024/12/pexels-kampus-8790298-scaled.jpg"
        },
        {
            "title": "How reading scientific storybooks and related conversations with children affect children’s persistence",
            "link": "https://childandfamilyblog.com/how-reading-scientific-storybooks-with-children-affects-persistence/?utm_source=rss&utm_medium=rss&utm_campaign=how-reading-scientific-storybooks-with-children-affects-persistence",
            "description": "Key takeaways for caregivers The messages caregivers convey in their conversations with preschool-aged children about science can affect children’s un...",
            "pubDate": "2025-05-31T19:56:16",
            "image_url": "https://childandfamilyblog.com/wp-content/uploads/2025/03/pexels-kindelmedia-7155304-scaled.jpg"
        },
        {
            "title": "Taking Summer Vacation, Turn Off and Tune Out",
            "link": "https://careersherpa.net/taking-summer-vacation-turn-off-and-tune-out/?utm_source=rss&utm_medium=rss&utm_campaign=taking-summer-vacation-turn-off-and-tune-out",
            "description": "Taking a summer vacation shouldn’t feel like a risk to your career—but for many, stepping away from work comes with guilt, anxiety, and a constant urg...",
            "pubDate": "2025-05-16T11:46:48",
            "image_url": "https://careersherpa.net/wp-content/uploads/2025/05/taking-vacation.png"
        },
        {
            "title": "Busy bodies, busy minds",
            "link": "https://childandfamilyblog.com/busy-bodies-busy-minds/?utm_source=rss&utm_medium=rss&utm_campaign=busy-bodies-busy-minds",
            "description": "Key takeaways for caregivers Appreciate busy babies: Through their grabbing, swinging, walking, jumping, babbling, and cooing, babies learn about the ...",
            "pubDate": "2025-05-13T06:41:20",
            "image_url": "https://childandfamilyblog.com/wp-content/uploads/2025/01/pexels-adrie-molco-1575393-3026858-scaled.jpg"
        },
        {
            "title": "Our Small Kitchen With Attached Living Area",
            "link": "https://www.younghouselove.com/our-small-kitchen-and-living-area/",
            "description": "I know a house always evolves to work with a family's changing needs, but I'd say this kitchen and attached sitting area are as close to absolutely do...",
            "pubDate": "2025-04-23T16:10:13",
            "image_url": "https://www.younghouselove.com/wp-content/uploads//2024/08/Small-Ikea-Kitchen-Seating-Area-With-Door-650x494.jpg"
        },
        {
            "title": "A Weekend In Serenbe, Georgia",
            "link": "https://www.younghouselove.com/serenbe-georgia-family-trip/",
            "description": "Serenbe is a small \"New Urban\" community about 45 minutes south of Atlanta in a rural town called Chattahoochee Hills. It's sort of a mix of an upscal...",
            "pubDate": "2025-04-04T17:02:21",
            "image_url": "https://www.younghouselove.com/wp-content/uploads//2025/03/Serenbe-Georiga-Stables-With-Sign-650x488.jpg"
        },
        {
            "title": "How To Propagate Succulents",
            "link": "https://www.younghouselove.com/how-to-propagate-succulents/",
            "description": "Succulents are some of the easiest houseplants to propagate because there are several ways to do it. Today we'll show how one succulent can be turned ...",
            "pubDate": "2025-03-04T20:19:23",
            "image_url": "https://www.younghouselove.com/wp-content/uploads//2024/06/Propagate-Succulent-4-Methods-Overhead-650x544.jpg"
        },
        {
            "title": "6 Ways NotebookLM AI Streamlines Your Entire Job Search",
            "link": "https://careersherpa.net/6-ways-notebooklm-ai-streamlines-your-entire-job-search/?utm_source=rss&utm_medium=rss&utm_campaign=6-ways-notebooklm-ai-streamlines-your-entire-job-search",
            "description": "NotebookLM’s AI-powered platform revolutionizes your job search by transforming how you customize cover letters and resumes, conduct targeted networki...",
            "pubDate": "2025-02-14T12:00:48",
            "image_url": "https://careersherpa.net/wp-content/uploads/2025/02/6-ways-NotebookLM-streamlines-job-search.png"
        },
        {
            "title": "Stop Chasing Jobs",
            "link": "https://careersherpa.net/stop-chasing-jobs/?utm_source=rss&utm_medium=rss&utm_campaign=stop-chasing-jobs",
            "description": "When you invest the bulk of your time only pursuing posted jobs, you are missing out of the opportunity to meet with individuals inside companies that...",
            "pubDate": "2025-02-12T10:30:00",
            "image_url": "https://careersherpa.net/wp-content/uploads/2025/04/stop-chasing-jobs-.png"
        },
        {
            "title": "HOW TO: 4 Ways to Update Your LinkedIn Status",
            "link": "https://careersherpa.net/how-to-4-ways-to-update-your-linkedin-status/?utm_source=rss&utm_medium=rss&utm_campaign=how-to-4-ways-to-update-your-linkedin-status",
            "description": "Do you want an easy way to stay connected with your network on LinkedIn? Or maybe you want employers to discover you. Updating your LinkedIn profile r...",
            "pubDate": "2025-02-11T10:43:00",
            "image_url": "https://careersherpa.net/wp-content/uploads/2025/04/ways-to-update-linkedin.png"
        },
        {
            "title": "Checklist for a Job Search",
            "link": "https://careersherpa.net/check-list-for-a-job-search/?utm_source=rss&utm_medium=rss&utm_campaign=check-list-for-a-job-search",
            "description": "Having a job search checklist ensures you have the right equipment and tools to compete. Without having everything you need, you potentially waste a l...",
            "pubDate": "2025-01-31T09:26:00",
            "image_url": "https://careersherpa.net/wp-content/uploads/2024/08/Checklist-for-Job-Search.png"
        },
        {
            "title": "A Weekend Getaway To Ocean Springs",
            "link": "https://www.younghouselove.com/a-weekend-getaway-to-ocean-springs/",
            "description": "Never heard of Ocean Springs, Mississippi? Neither had we! But it caught our eye on round-ups like Southern Living's 15 Most Adorable Small Towns and ...",
            "pubDate": "2025-01-25T15:19:38",
            "image_url": "https://www.younghouselove.com/wp-content/uploads//2024/11/Ocean-Springs-Featured-Image-Cash-Alleys-650x546.jpg"
        },
        {
            "title": "2024 Holiday Gift Guides",
            "link": "https://www.younghouselove.com/holiday-gift-guides-2024/",
            "description": "Just like we did for our 2023 Gift Guides and our 2022 Gift Guides , we’ve got all three of our gift lists in one singular post right here. So let’s d...",
            "pubDate": "2024-11-21T05:12:16",
            "image_url": "https://www.younghouselove.com/wp-content/uploads//2024/11/2024-Holiday-Gift-Guide-Featured-Image-650x390.jpg"
        }
    ]
}